temporalvector/__init__.py
temporalvector/temporal_enums.py
temporalvector/temporal_vector.py
temporalvector-1.0.0.dist-info/METADATA
temporalvector-1.0.0.dist-info/WHEEL
temporalvector-1.0.0.dist-info/licenses/LICENSE
temporalvector-1.0.0.dist-info/RECORD
