Metadata-Version: 2.1
Name: temporalvector
Version: 1.0.0
Summary: Temporally aware vector of values that can be aggregated using different methods over different time periods
Project-URL: Homepage, https://github.com/crmckay55/sim_pkg_temporal_vector.git
Author-email: Chris McKay <crmckay55@gmail.com>
License-File: LICENSE
Classifier: License :: OSI Approved :: MIT License
Classifier: Operating System :: OS Independent
Classifier: Programming Language :: Python :: 3
Requires-Python: >=3.10
